Workbook

Sheet Hoja1
A1: cod_lre | B1: concepto_detalle | C1: Tipo
A2: Viáticos(2303) | B2: viaticoMi | C2: Haber exento
A3: Tratos(2112) | B3: tratoMi | C3: Haber afecto
A4: Total líquido(5501) | B4: totalesEmpl | C4: Descuento
A5: Sueldo(2101) | B5: sueldoBase | C5: Haber afecto
A6: Sueldo empresarial (2161) | B6: sueldoBase | C6: Haber afecto
A7: Subsidio por incapacidad laboral por licencia médica(2201) | B7: otrosHaberes | C7: Haber afecto
A8: Sobresueldo(2102) | B8: sobresueldoMi | C8: Haber afecto
A9: Semana corrida(2104) | B9: semanaCorr | C9: Haber afecto
A10: Sala cuna(2308) | B10: salaCMi | C10: Haber exento
A11: Retención préstamo clase media 2020 (Ley 21.252) (3166) | B11: solidarioremu | C11: Descuento Legal
A12: Remuneraciones trimestrales(2117) | B12: otrosHaberes | C12: Haber afecto
... A94: AFC - Aporte empleador(4151) | B94: cesAporteCi | C94: Aporte Empleador

Sheet Hoja2
F1: Fecha de proceso | G1: Fecha de proceso
B2: Fecha de proceso | F2: Id empleado | G2: Id empleado
B3: Id empleado | F3: Número de contrato | G3: Número de contrato
B4: Número de contrato | F4: Id del concepto
B5: Id de empresa | F5: Monto del concepto
B6: afp | F6: Afecto
B7: %afp | F7: Id de institución | G7: afp | H7: isapre | I7: mutual | J7: Ccaf
B8: isapre | F8: Cotización de jubilación | G8: %afp | H8: % mutual | I8: %Sis | J8: % mutual | K8: 0.6 | L8: %ccaf
B9: Ccaf | F9: Días de licencias | G9: Nro días de licencia médica
B10: % Ccaf | F10: Días trabajados | G10: Nro días trabajados
B11: Mutual | F11: Fecha de aplicación
B12: % mutual | F12: Empresa | G12: Id de empresa
B13: %Sis | F13: Total de rebajas por LLSS
B14: Nro días trabajados | F14: Rentas no gravadas
B15: Nro días de licencia médica | C15: licenciaDias | F15: Rebaja por zona extrema
B16: Sueldo(2101) | C16: =VLOOKUP(B16,Hoja1!A:B,2,0) -> sueldoBase | F16: Jornada
B17: Sobresueldo(2102) | C17: =VLOOKUP(B17,Hoja1!A:B,2,0) -> sobresueldoMi | F17: Días de vacaciones
B18: Comisiones(2103) | C18: =VLOOKUP(B18,Hoja1!A:B,2,0) -> comisionMi | F18: Monto Init
B19: Semana corrida(2104) | C19: =VLOOKUP(B19,Hoja1!A:B,2,0) -> semanaCorr | F19: Fase
B20: Participación(2105) | C20: =VLOOKUP(B20,Hoja1!A:B,2,0) -> participacionMi
B21: Gratificación(2106) | C21: =VLOOKUP(B21,Hoja1!A:B,2,0) -> gratificacion
B22: Recargo 30% día domingo (Art. 38) (2107) | C22: recargoMi
B23: Remuneración variable pagada en vacaciones (Art 71) (cód 2108) | C23: remvarMi
B24: Aguinaldo(2110) | C24: =VLOOKUP(B24,Hoja1!A:B,2,0) -> AguinaldoMi
B25: Bonos u otras remun. fijas mensuales(2111) | C25: =VLOOKUP(B25,Hoja1!A:B,2,0) -> BonoMi
B26: Tratos (mensual) (cód 2112) | C26: tratoMi
B27: Bonos u otras remuneraciones variables mensuales o superiores a un mes (cód 2113) | C27: bonsupMi
B28: Beneficios en especie constitutivos de remuneración (cód 2115) | C28: benefMi
B29: Otras remuneraciones superiores a un mes (cód 2123) | C29: otremMi
B30: Pago por horas de trabajo sindical (cód 2124) | C30: pagosindMi
B31: Subsidio por incapacidad laboral por licencia médica(2201) | C31: =VLOOKUP(B31,Hoja1!A:B,2,0) -> otrosHaberes
B32: Beca de estudio (Art. 17 N°18 LIR) (cód 2202) | C32: otrosHaberes
B33: Otros ingresos no constitutivos de renta (Art 17 N°29 LIR) (cód 2204) | C33: otingrMi
B34: Colación(2301) | C34: =VLOOKUP(B34,Hoja1!A:B,2,0) -> colacion
B35: Movilización(2302) | C35: =VLOOKUP(B35,Hoja1!A:B,2,0) -> movilizacion
B36: Viáticos totales mensual (Art 41) (cód 2303) | C36: gastoMi
B37: Asignación de pérdida de caja(2304) | C37: =VLOOKUP(B37,Hoja1!A:B,2,0) -> asigPerdCajaMi
B38: Asignación de desgaste herramienta(2305) | C38: =VLOOKUP(B38,Hoja1!A:B,2,0) -> AsigDesgHerrMi
B39: Gastos por causa del trabajo (Art 41 CdT) y gastos de representación (Art. 42 Nº1 LIR) (cód 2306) | C39: salaCMi
B40: Sala cuna (Art 203) (cód 2308) | C40: salaCMi
B41: Asignación familiar legal(2311) | C41: =VLOOKUP(B41,Hoja1!A:B,2,0) -> cargasSimp
B42: Asignación trabajo a distancia o teletrabajo(2309) | C42: =VLOOKUP(B42,Hoja1!A:B,2,0) -> AsigTeletrabajoMi
B43: Alojamiento por razones de trabajo (2310) | C43: alojamientoTrabajoMi
B44: Asignación de traslación(2312) | C44: =VLOOKUP(B44,Hoja1!A:B,2,0) -> TraslacionMi
B45: Indemnización por feriado legal(2313) | C45: =VLOOKUP(B45,Hoja1!A:B,2,0) -> iasVacaciones
B46: Indemnización años de servicio(2314) | C46: =VLOOKUP(B46,Hoja1!A:B,2,0) -> iasLegal
B47: Indemnización sustitutiva del aviso previo(2315) | C47: =VLOOKUP(B47,Hoja1!A:B,2,0) -> iasMes
B48: Indemnización fuero maternal (Art 163 bis) (cód 2316) | C48: indemMMi
B49: Indemnización a todo evento (Art.164) (cód 2331) | C49: indemNMi
B50: Indemnizaciones voluntarias tributables (cód 2417) | C50: iasVoluntaria
B51: Indemnizaciones contractuales tributables (cód 2418) | C51: iasafecta
B52: Cotización obligatoria previsional (AFP o IPS)(3141) | C52: =VLOOKUP(B52,Hoja1!A:B,2,0) -> afp
B53: Cotización obligatoria salud 7%(3143) | C53: =VLOOKUP(B53,Hoja1!A:B,2,0) -> isapre
B54: Cotización voluntaria para salud(3144) | C54: =VLOOKUP(B54,Hoja1!A:B,2,0) -> isapre
B55: Cotización AFC - trabajador(3151) | C55: =VLOOKUP(B55,Hoja1!A:B,2,0) -> cesEmpleado
B56: Cotización adicional trabajo pesado- trabajador (cód 3154) | C56: trabajoPesaEmpl
B57: Cotización APVi Mod A(3155) | C57: =VLOOKUP(B57,Hoja1!A:B,2,0) -> apvi
B58: Cotización APVi Mod B hasta UF50(3156) | C58: =VLOOKUP(B58,Hoja1!A:B,2,0) -> apvi
B59: Impuesto retenido por remuneraciones(3161) | C59: =VLOOKUP(B59,Hoja1!A:B,2,0) -> impuesto
B60: Impuesto retenido por indemnizaciones (cód 3162) | C60: imptoindMi
B61: Mayor retención de impuesto solicitada por el trabajador (cód 3163) | C61: ppm
B62: Impuesto retenido por reliquidación de remuneraciones devengadas en otros períodos mensuales (cód 3164) | C62: reliquidaImpuesto
B63: Retención préstamo clase media 2020 (Ley 21.252) (3166) | C63: =VLOOKUP(B63,Hoja1!A:B,2,0) -> solidarioremu
B64: Cuota sindical 1(3171) | C64: =VLOOKUP(B64,Hoja1!A:B,2,0) -> CuotaSindMi
B65: Crédito social CCAF(3110) | C65: =VLOOKUP(B65,Hoja1!A:B,2,0) -> cajaCred
B66: Cuota vivienda o educación Art. 58 (cód 3181) | C66: cuotavivMi
B67: Crédito cooperativas de ahorro (Art 54 Ley Coop.) (cód 3182) | C67: credMi
B68: Otros descuentos autorizados y solicitados por el trabajador (cód 3183) | C68: otrdescMi
B69: Otros descuentos(3185) | C69: =VLOOKUP(B69,Hoja1!A:B,2,0) -> otrosDesctoMi
B70: Pensiones de alimentos(3186) | C70: =VLOOKUP(B70,Hoja1!A:B,2,0) -> retencionJudicial
B71: Descuentos por anticipos y préstamos(3188) | C71: =VLOOKUP(B71,Hoja1!A:B,2,0) -> AnticipoPrestamoMi
B72: AFC - Aporte empleador solidario | C72: cesAporteSol
B73: AFC - Aporte empleador individual | C73: cesAporteCi
B74: Aporte empleador seguro accidentes del trabajo y Ley SANNA(4152) | C74: =VLOOKUP(B74,Hoja1!A:B,2,0) -> mutual
B75: Aporte adicional trabajo pesado- empleador (cód 4154) | C75: trabajoPesa
B76: Rebaja zona extrema DL 889 (3167) | C76: =VLOOKUP(B76,Hoja1!A:B,2,0) -> zonaExtrema
B77: Aporte empleador seguro invalidez y sobrevivencia(4155) | C77: =VLOOKUP(B77,Hoja1!A:B,2,0) -> sis
B78: Total líquido(5501) | C78: =VLOOKUP(B78,Hoja1!A:B,2,0) -> totalesEmpl
B79: jornada | C79: C
